infracraft/__init__.py
infracraft/cli.py
infracraft-0.0.1.dist-info/METADATA
infracraft-0.0.1.dist-info/WHEEL
infracraft-0.0.1.dist-info/top_level.txt
infracraft-0.0.1.dist-info/RECORD
